LICENSE.txt
MANIFEST.in
README.rst
TODO
pavement.py
requirements.txt
setup.py
docs/api.rst
docs/conf.py
docs/help.rst
docs/index.rst
docs/readme.rst
docs/screen.rst
docs/struct.rst
psidialogs/__init__.py
psidialogs/attribdict.py
psidialogs/backend_api.py
psidialogs/backendloader.py
psidialogs/iplugin.py
psidialogs/loader.py
psidialogs/mixins.py
psidialogs/singl.py
psidialogs/unicodeutil.py
psidialogs.egg-info/PKG-INFO
psidialogs.egg-info/SOURCES.txt
psidialogs.egg-info/dependency_links.txt
psidialogs.egg-info/not-zip-safe
psidialogs.egg-info/requires.txt
psidialogs.egg-info/top_level.txt
psidialogs/api/__init__.py
psidialogs/api/ask_number.py
psidialogs/api/easydialogs_api.py
psidialogs/api/easygui_api.py
psidialogs/api/tkfiledialog_api.py
psidialogs/api/tkmessagebox_api.py
psidialogs/api/tksimpledialog_api.py
psidialogs/api/wxlibdialogs_api.py
psidialogs/examples/__init__.py
psidialogs/examples/demo.py
psidialogs/examples/easygui_test.py
psidialogs/examples/opendialog.py
psidialogs/examples/wxlibdialogs_test.py
psidialogs/plugins/__init__.py
psidialogs/plugins/console_wrapper.py
psidialogs/plugins/easydialogs_wrapper.py
psidialogs/plugins/easygui_wrapper.py
psidialogs/plugins/gmessage_wrapper.py
psidialogs/plugins/pygtk_wrapper.py
psidialogs/plugins/pyqt_wrapper.py
psidialogs/plugins/pythondialog_wrapper.py
psidialogs/plugins/tkinter_wrapper.py
psidialogs/plugins/wxpython_wrapper.py
psidialogs/plugins/zenity_wrapper.py