Metadata-Version: 1.1
Name: psidialogs
Version: 0.1.0
Summary: python simple dialogs
Home-page: https://github.com/ponty/psidialogs
Author: ponty
Author-email: UNKNOWN
License: BSD
Keywords: GUI common dialog
Platform: UNKNOWN
Classifier: License :: OSI Approved :: BSD License
Classifier: Natural Language :: English
Classifier: Operating System :: OS Independent
Classifier: Programming Language :: Python
